pyrex/__init__.py
pyrex/exceptions.py
pyrex/py.typed
pyrex/core/__init__.py
pyrex/core/base.py
pyrex/core/compiler.py
pyrex/core/types.py
pyrex/languages/__init__.py
pyrex/languages/c.py
pyrex/languages/cpp.py
pyrex/languages/rust.py
pyrex/utils/__init__.py
pyrex/utils/cache.py
pyrex/utils/errors.py
pyrex/utils/helpers.py
pyrex/utils/security.py
pyrex3-1.0.4.dist-info/licenses/LICENSE
pyrex3-1.0.4.dist-info/METADATA
pyrex3-1.0.4.dist-info/WHEEL
pyrex3-1.0.4.dist-info/top_level.txt
pyrex3-1.0.4.dist-info/RECORD
