Metadata-Version: 2.4
Name: pyrex3
Version: 1.0.4
Summary: Lightning-fast multi-language code execution engine with security-first design
Author-email: kendroooo <sudo@shiro.lol>
Maintainer-email: kendroooo <sudo@shiro.lol>
License: MIT
Project-URL: Homepage, https://github.com/kendroooo/pyrex
Project-URL: Repository, https://github.com/kendroooo/pyrex.git
Project-URL: Discussions, https://github.com/kendroooo/pyrex/discussions
Keywords: compiler,rust,c,cpp,execution,fast,security,multi-language,code-execution,performance
Classifier: Development Status :: 5 - Production/Stable
Classifier: Intended Audience :: Developers
Classifier: Intended Audience :: Education
Classifier: Intended Audience :: Science/Research
Classifier: License :: OSI Approved :: MIT License
Classifier: Operating System :: OS Independent
Classifier: Programming Language :: Python :: 3
Classifier: Programming Language :: Python :: 3.8
Classifier: Programming Language :: Python :: 3.9
Classifier: Programming Language :: Python :: 3.10
Classifier: Programming Language :: Python :: 3.11
Classifier: Programming Language :: Python :: 3.12
Classifier: Programming Language :: Rust
Classifier: Programming Language :: C
Classifier: Programming Language :: C++
Classifier: Topic :: Software Development :: Compilers
Classifier: Topic :: Software Development :: Interpreters
Classifier: Topic :: System :: Systems Administration
Classifier: Topic :: Utilities
Classifier: Typing :: Typed
Requires-Python: >=3.8
License-File: LICENSE
Requires-Dist: typing-extensions>=4.0.0
Requires-Dist: pathlib2>=2.3.0; python_version < "3.4"
Requires-Dist: dataclasses>=0.6; python_version < "3.7"
Provides-Extra: dev
Requires-Dist: black>=23.0.0; extra == "dev"
Requires-Dist: isort>=5.12.0; extra == "dev"
Requires-Dist: flake8>=6.0.0; extra == "dev"
Requires-Dist: mypy>=1.0.0; extra == "dev"
Requires-Dist: pre-commit>=3.0.0; extra == "dev"
Requires-Dist: tox>=4.0.0; extra == "dev"
Dynamic: license-file
